pylettize/__init__.py
pylettize/cli.py
pylettize/palettes/__init__.py
pylettize/palettes/gruvbox
pylettize/palettes/obama
pylettize/palettes/primaries
pylettize/pylettize.py
pylettize-0.1.2.dist-info/LICENSE
pylettize-0.1.2.dist-info/METADATA
pylettize-0.1.2.dist-info/WHEEL
pylettize-0.1.2.dist-info/entry_points.txt
pylettize-0.1.2.dist-info/RECORD
