Metadata-Version: 2.1
Name: pylettize
Version: 0.1.2
Summary: Customize the palette of any input image
License: MIT
Author: Frans Johansson
Author-email: fransjohansson98@gmail.com
Requires-Python: >=3.8.1,<4.0.0
Classifier: License :: OSI Approved :: MIT License
Classifier: Programming Language :: Python :: 3
Classifier: Programming Language :: Python :: 3.9
Classifier: Programming Language :: Python :: 3.10
Classifier: Programming Language :: Python :: 3.11
Requires-Dist: docopt (>=0.6.2,<0.7.0)
Requires-Dist: numpy (>=1.24.2,<2.0.0)
Requires-Dist: scikit-image (>=0.20.0,<0.21.0)
